LICENSE
README.md
setup.py
battleships/__init__.py
battleships/advanced_ai.py
battleships/ai_comparison.py
battleships/components.py
battleships/game_engine.py
battleships/main.py
battleships/mp_game_engine.py
battleships/templates/entry.html
battleships/templates/main.html
battleships/templates/placement.html
battleships_edf1101.egg-info/PKG-INFO
battleships_edf1101.egg-info/SOURCES.txt
battleships_edf1101.egg-info/dependency_links.txt
battleships_edf1101.egg-info/top_level.txt
tests/__init__.py
tests/test_advanced_ai.py
tests/test_ai_comparison.py
tests/test_components.py
tests/test_game_engine.py
tests/test_helper_functions.py
tests/test_mp_game_engine.py
tests/test_students.py