Metadata-Version: 2.1
Name: battleships-edf1101
Version: 1.0.1
Summary: 2023 ECM1400 Coursework - Battleships
Home-page: https://github.com/edf1101/Battleships
Author: Ed Fillingham
Author-email: ef494@exeter.ac.uk
Classifier: Programming Language :: Python :: 3
Classifier: License :: OSI Approved :: MIT License
Classifier: Operating System :: OS Independent
Requires-Python: >=3.11.4
License-File: LICENSE
